essence/__init__.py
essence/base.py
essence/component.py
essence/entity.py
essence/system.py
essence/world.py
essence-0.0.2.dist-info/DESCRIPTION.rst
essence-0.0.2.dist-info/METADATA
essence-0.0.2.dist-info/RECORD
essence-0.0.2.dist-info/WHEEL
essence-0.0.2.dist-info/metadata.json
essence-0.0.2.dist-info/top_level.txt
