Metadata-Version: 2.0
Name: essence
Version: 0.0.2
Summary: UNKNOWN
Home-page: https://github.com/chromy/essence.git
Author: Hector Dearman
Author-email: hector.dearman@gmail.com
License: MIT
Platform: UNKNOWN
Classifier: Development Status :: 3 - Alpha
Classifier: Intended Audience :: Developers
Classifier: License :: OSI Approved :: MIT License
Classifier: Programming Language :: Python :: 2
Classifier: Programming Language :: Python :: 2.6
Classifier: Programming Language :: Python :: 2.7
Classifier: Programming Language :: Python :: 3
Classifier: Programming Language :: Python :: 3.2
Classifier: Programming Language :: Python :: 3.3
Classifier: Programming Language :: Python :: 3.4
Requires-Dist: sortedcontainers
Requires-Dist: total-ordering
